great_ape_safe/__init__.py
great_ape_safe/great_ape_safe.py
great_ape_safe/api_safe/__init__.py
great_ape_safe/api_safe/aave.py
great_ape_safe/api_safe/compound.py
great_ape_safe/api_safe/convex.py
great_ape_safe/api_safe/curve.py
great_ape_safe-0.0.1.dist-info/LICENSE
great_ape_safe-0.0.1.dist-info/WHEEL
great_ape_safe-0.0.1.dist-info/METADATA
great_ape_safe-0.0.1.dist-info/RECORD
