Metadata-Version: 2.1
Name: great_ape_safe
Version: 0.0.1
Summary: An extension of the legendary Ape Safe web3 package. Adding extra functions and making it protocol aware, saving time getting familiar with the source code of every individual smart contract.
Author-email: "Gosuto B.V." <mail@gosuto.ai>
Classifier: License :: OSI Approved :: GNU General Public License v3 or later (GPLv3+)
Requires-Dist: ape-safe
Requires-Dist: eth-brownie==1.17.0
Requires-Dist: pandas
Requires-Dist: rich
Requires-Dist: tqdm
Project-URL: Home, https://github.com/gosuto-ai/great-ape-safe
